Workbook
Name Slicer_channel: #N/A
Name Slicer_month: #N/A

Sheet retail_campaigns
A1: campaign_id | B1: name | C1: start_date | D1: end_date | E1: budget
A2: MKT-01 | B2: Summer Sale | C2: 45078 | D2: 45107 | E2: 5000
A3: MKT-02 | B3: Black Friday | C3: 45250 | D3: 45260 | E3: 12000
A4: MKT-03 | B4: Holiday Cheer | C4: 45275 | D4: 45291 | E4: 8000
A5: MKT-04 | B5: New Year Refresh | C5: 45292 | D5: 45306 | E5: 4000

Sheet retail_products
A1: product_id | B1: product_name | C1: category | D1: unit_cost | E1: unit_price | F1: stock_level
A2: P-2001 | B2: Home Decor Item 1 | C2: Home Decor | D2: 438.33 | E2: 1011.63 | F2: 184
A3: P-2002 | B3: Apparel Item 2 | C3: Apparel | D3: 218.74 | E3: 295.45 | F3: 435
A4: P-2003 | B4: Electronics Item 3 | C4: Electronics | D4: 14.74 | E4: 20.34 | F4: 331
A5: P-2004 | B5: Home Decor Item 4 | C5: Home Decor | D5: 171.04 | E5: 404.15 | F5: 489
A6: P-2005 | B6: Sports Item 5 | C6: Sports | D6: 141.47 | E6: 304.58 | F6: 190
A7: P-2006 | B7: Apparel Item 6 | C7: Apparel | D7: 99.61 | E7: 171.43 | F7: 492
A8: P-2007 | B8: Beauty Item 7 | C8: Beauty | D8: 143.2 | E8: 243.64 | F8: 435
A9: P-2008 | B9: Beauty Item 8 | C9: Beauty | D9: 401.95 | E9: 821.38 | F9: 408
A10: P-2009 | B10: Home Decor Item 9 | C10: Home Decor | D10: 65.4 | E10: 137.67 | F10: 30
A11: P-2010 | B11: Home Decor Item 10 | C11: Home Decor | D11: 60.82 | E11: 145.03 | F11: 247
A12: P-2011 | B12: Sports Item 11 | C12: Sports | D12: 342.41 | E12: 491.58 | F12: 194
A13: P-2012 | B13: Apparel Item 12 | C13: Apparel | D13: 309.57 | E13: 718.62 | F13: 450
... A51: P-2050 | B51: Apparel Item 50 | C51: Apparel | D51: 231.89 | E51: 318.47 | F51: 211

Sheet retail_customers
A1: customer_id | B1: age | C1: gender | D1: region | E1: segment | F1: signup_date
A2: CUST-1000 | B2: 58 | C2: Male | D2: North | E2: Bronze | F2: 44478
A3: CUST-1001 | B3: 33 | C3: Male | D3: South | E3: Bronze | F3: 44301
A4: CUST-1002 | B4: 61 | C4: Other | D4: North | E4: Bronze | F4: 44629
A5: CUST-1003 | B5: 20 | C5: Male | D5: North | E5: Gold | F5: 44435
A6: CUST-1004 | B6: 50 | C6: Other | D6: North | E6: Bronze | F6: 44400
A7: CUST-1005 | B7: 63 | C7: Other | D7: West | E7: Gold | F7: 44656
A8: CUST-1006 | B8: 55 | C8: Female | D8: North | E8: Gold | F8: 44911
A9: CUST-1007 | B9: 45 | C9: Female | D9: East | E9: Gold | F9: 44417
A10: CUST-1008 | B10: 66 | C10: Female | D10: North | E10: Gold | F10: 44586
A11: CUST-1009 | B11: 24 | C11: Female | D11: East | E11: Bronze | F11: 44467
A12: CUST-1010 | B12: 69 | C12: Male | D12: West | E12: Bronze | F12: 44324
A13: CUST-1011 | B13: 42 | C13: Male | D13: East | E13: Bronze | F13: 44830
... A1001: CUST-1999 | B1001: 36 | C1001: Female | D1001: West | E1001: Gold | F1001: 44299

Sheet retail_sales
A1: order_id | B1: order_date | C1: customer_id | D1: product_id | E1: quantity | F1: quantity edited | G1: channel | H1: discount_applied | I1: unit_price | J1: unit_cost | K1: gross_revenue | L1: discount_amount | M1: net_revenue | N1: profit | O1: month
A2: ORD-50001 | B2: 45235 | C2: CUST-1716 | D2: P-2048 | E2: 5 | F2: =IF(E2<0,0,E2) -> 5 | G2: Mobile App | H2: 0.17 | I2: =_xlfn.XLOOKUP(D2, 'retail_products'!$A:$A, 'retail_products'!$E:$E, "") -> 436.93 | J2: =_xlfn.XLOOKUP(D2, 'retail_products'!$A:$A, 'retail_products'!$D:$D, "") -> 257.01 | K2: =E2*I2 -> 2184.65 | L2: =K2*H2 -> 371.3905 | M2: =K2-L2 -> 1813.2595 | N2: =M2-(E2*J2) -> 528.2095 | O2: =TEXT(B2,"mmm") -> Nov
A3: ORD-50002 | B3: 45038 | C3: CUST-1205 | D3: P-2014 | E3: 5 | F3: =IF(E3<0,0,E3) -> 5 | G3: Online | H3: 0.2 | I3: =_xlfn.XLOOKUP(D3, 'retail_products'!$A:$A, 'retail_products'!$E:$E, "") -> 289.73 | J3: =_xlfn.XLOOKUP(D3, 'retail_products'!$A:$A, 'retail_products'!$D:$D, "") -> 225.94 | K3: =E3*I3 -> 1448.65 | L3: =K3*H3 -> 289.73 | M3: =K3-L3 -> 1158.92 | N3: =M3-(E3*J3) -> 29.22 | O3: =TEXT(B3,"mmm") -> Apr
A4: ORD-50003 | B4: 45018 | C4: CUST-1515 | D4: P-2035 | E4: 3 | F4: =IF(E4<0,0,E4) -> 3 | G4: Mobile App | H4: 0 | I4: =_xlfn.XLOOKUP(D4, 'retail_products'!$A:$A, 'retail_products'!$E:$E, "") -> 403.95 | J4: =_xlfn.XLOOKUP(D4, 'retail_products'!$A:$A, 'retail_products'!$D:$D, "") -> 177.26 | K4: =E4*I4 -> 1211.85 | L4: =K4*H4 -> 0 | M4: =K4-L4 -> 1211.85 | N4: =M4-(E4*J4) -> 680.07 | O4: =TEXT(B4,"mmm") -> Apr
A5: ORD-50004 | B5: 45268 | C5: CUST-1727 | D5: P-2027 | E5: 5 | F5: =IF(E5<0,0,E5) -> 5 | G5: Mobile App | H5: 0 | I5: =_xlfn.XLOOKUP(D5, 'retail_products'!$A:$A, 'retail_products'!$E:$E, "") -> 458.87 | J5: =_xlfn.XLOOKUP(D5, 'retail_products'!$A:$A, 'retail_products'!$D:$D, "") -> 375.17 | K5: =E5*I5 -> 2294.35 | L5: =K5*H5 -> 0 | M5: =K5-L5 -> 2294.35 | N5: =M5-(E5*J5) -> 418.5 | O5: =TEXT(B5,"mmm") -> Dec
A6: ORD-50005 | B6: 45122 | C6: CUST-1148 | D6: P-2004 | E6: 1 | F6: =IF(E6<0,0,E6) -> 1 | G6: In-Store | H6: 0 | I6: =_xlfn.XLOOKUP(D6, 'retail_products'!$A:$A, 'retail_products'!$E:$E, "") -> 404.15 | J6: =_xlfn.XLOOKUP(D6, 'retail_products'!$A:$A, 'retail_products'!$D:$D, "") -> 171.04 | K6: =E6*I6 -> 404.15 | L6: =K6*H6 -> 0 | M6: =K6-L6 -> 404.15 | N6: =M6-(E6*J6) -> 233.11 | O6: =TEXT(B6,"mmm") -> Jul
A7: ORD-50006 | B7: 45001 | C7: CUST-1859 | D7: P-2004 | E7: 3 | F7: =IF(E7<0,0,E7) -> 3 | G7: In-Store | H7: 0 | I7: =_xlfn.XLOOKUP(D7, 'retail_products'!$A:$A, 'retail_products'!$E:$E, "") -> 404.15 | J7: =_xlfn.XLOOKUP(D7, 'retail_products'!$A:$A, 'retail_products'!$D:$D, "") -> 171.04 | K7: =E7*I7 -> 1212.45 | L7: =K7*H7 -> 0 | M7: =K7-L7 -> 1212.45 | N7: =M7-(E7*J7) -> 699.33 | O7: =TEXT(B7,"mmm") -> Mar
A8: ORD-50007 | B8: 45371 | C8: CUST-1691 | D8: P-2048 | E8: 5 | F8: =IF(E8<0,0,E8) -> 5 | G8: Online | H8: 0 | I8: =_xlfn.XLOOKUP(D8, 'retail_products'!$A:$A, 'retail_products'!$E:$E, "") -> 436.93 | J8: =_xlfn.XLOOKUP(D8, 'retail_products'!$A:$A, 'retail_products'!$D:$D, "") -> 257.01 | K8: =E8*I8 -> 2184.65 | L8: =K8*H8 -> 0 | M8: =K8-L8 -> 2184.65 | N8: =M8-(E8*J8) -> 899.6 | O8: =TEXT(B8,"mmm") -> Mar
A9: ORD-50008 | B9: 45334 | C9: CUST-1817 | D9: P-2045 | E9: 3 | F9: =IF(E9<0,0,E9) -> 3 | G9: In-Store | H9: 0.29 | I9: =_xlfn.XLOOKUP(D9, 'retail_products'!$A:$A, 'retail_products'!$E:$E, "") -> 769.55 | J9: =_xlfn.XLOOKUP(D9, 'retail_products'!$A:$A, 'retail_products'!$D:$D, "") -> 421.02 | K9: =E9*I9 -> 2308.65 | L9: =K9*H9 -> 669.5085 | M9: =K9-L9 -> 1639.1415 | N9: =M9-(E9*J9) -> 376.0815 | O9: =TEXT(B9,"mmm") -> Feb
B10: 45087 | C10: CUST-1989 | D10: P-2036 | E10: 1 | F10: =IF(E10<0,0,E10) -> 1 | G10: In-Store | H10: 0.27 | I10: =_xlfn.XLOOKUP(D10, 'retail_products'!$A:$A, 'retail_products'!$E:$E, "") -> 469.35 | J10: =_xlfn.XLOOKUP(D10, 'retail_products'!$A:$A, 'retail_products'!$D:$D, "") -> 278.37 | K10: =E10*I10 -> 469.35 | L10: =K10*H10 -> 126.7245 | M10: =K10-L10 -> 342.6255 | N10: =M10-(E10*J10) -> 64.2555 | O10: =TEXT(B10,"mmm") -> Jun
A11: ORD-50010 | B11: 45287 | C11: CUST-1726 | D11: P-2042 | E11: 3 | F11: =IF(E11<0,0,E11) -> 3 | G11: Mobile App | H11: 0.09 | I11: =_xlfn.XLOOKUP(D11, 'retail_products'!$A:$A, 'retail_products'!$E:$E, "") -> 693.46 | J11: =_xlfn.XLOOKUP(D11, 'retail_products'!$A:$A, 'retail_products'!$D:$D, "") -> 388.35 | K11: =E11*I11 -> 2080.38 | L11: =K11*H11 -> 187.2342 | M11: =K11-L11 -> 1893.1458 | N11: =M11-(E11*J11) -> 728.0958 | O11: =TEXT(B11,"mmm") -> Dec
A12: ORD-50011 | B12: 45017 | C12: CUST-1699 | D12: P-2005 | E12: 2 | F12: =IF(E12<0,0,E12) -> 2 | G12: Online | H12: 0 | I12: =_xlfn.XLOOKUP(D12, 'retail_products'!$A:$A, 'retail_products'!$E:$E, "") -> 304.58 | J12: =_xlfn.XLOOKUP(D12, 'retail_products'!$A:$A, 'retail_products'!$D:$D, "") -> 141.47 | K12: =E12*I12 -> 609.16 | L12: =K12*H12 -> 0 | M12: =K12-L12 -> 609.16 | N12: =M12-(E12*J12) -> 326.22 | O12: =TEXT(B12,"mmm") -> Apr
A13: ORD-50012 | B13: 45211 | C13: CUST-1270 | D13: P-2009 | E13: 2 | F13: =IF(E13<0,0,E13) -> 2 | G13: Mobile App | H13: 0.01 | I13: =_xlfn.XLOOKUP(D13, 'retail_products'!$A:$A, 'retail_products'!$E:$E, "") -> 137.67 | J13: =_xlfn.XLOOKUP(D13, 'retail_products'!$A:$A, 'retail_products'!$D:$D, "") -> 65.4 | K13: =E13*I13 -> 275.34 | L13: =K13*H13 -> 2.7534 | M13: =K13-L13 -> 272.5866 | N13: =M13-(E13*J13) -> 141.7866 | O13: =TEXT(B13,"mmm") -> Oct
A14: ORD-50013 | B14: 45092 | C14: CUST-1611 | D14: P-2004 | E14: 5 | F14: =IF(E14<0,0,E14) -> 5 | G14: Mobile App | H14: 0 | I14: =_xlfn.XLOOKUP(D14, 'retail_products'!$A:$A, 'retail_products'!$E:$E, "") -> 404.15 | J14: =_xlfn.XLOOKUP(D14, 'retail_products'!$A:$A, 'retail_products'!$D:$D, "") -> 171.04 | K14: =E14*I14 -> 2020.75 | L14: =K14*H14 -> 0 | M14: =K14-L14 -> 2020.75 | N14: =M14-(E14*J14) -> 1165.55 | O14: =TEXT(B14,"mmm") -> Jun
A15: ORD-50014 | B15: 45328 | C15: CUST-1724 | D15: P-2021 | E15: 5 | F15: =IF(E15<0,0,E15) -> 5 | G15: Mobile App | H15: 0 | I15: =_xlfn.XLOOKUP(D15, 'retail_products'!$A:$A, 'retail_products'!$E:$E, "") -> 466.51 | J15: =_xlfn.XLOOKUP(D15, 'retail_products'!$A:$A, 'retail_products'!$D:$D, "") -> 257.73 | K15: =E15*I15 -> 2332.55 | L15: =K15*H15 -> 0 | M15: =K15-L15 -> 2332.55 | N15: =M15-(E15*J15) -> 1043.9 | O15: =TEXT(B15,"mmm") -> Feb
A16: ORD-50015 | B16: 45205 | C16: CUST-1549 | D16: P-2026 | E16: 1 | F16: =IF(E16<0,0,E16) -> 1 | G16: In-Store | H16: 0 | I16: =_xlfn.XLOOKUP(D16, 'retail_products'!$A:$A, 'retail_products'!$E:$E, "") -> 765.43 | J16: =_xlfn.XLOOKUP(D16, 'retail_products'!$A:$A, 'retail_products'!$D:$D, "") -> 429.73 | K16: =E16*I16 -> 765.43 | L16: =K16*H16 -> 0 | M16: =K16-L16 -> 765.43 | N16: =M16-(E16*J16) -> 335.7 | O16: =TEXT(B16,"mmm") -> Oct
A17: ORD-50016 | B17: 45038 | C17: CUST-1973 | D17: P-2049 | E17: 5 | F17: =IF(E17<0,0,E17) -> 5 | G17: Mobile App | H17: 0 | I17: =_xlfn.XLOOKUP(D17, 'retail_products'!$A:$A, 'retail_products'!$E:$E, "") -> 353.33 | J17: =_xlfn.XLOOKUP(D17, 'retail_products'!$A:$A, 'retail_products'!$D:$D, "") -> 144.06 | K17: =E17*I17 -> 1766.65 | L17: =K17*H17 -> 0 | M17: =K17-L17 -> 1766.65 | N17: =M17-(E17*J17) -> 1046.35 | O17: =TEXT(B17,"mmm") -> Apr
A18: ORD-50017 | B18: 45269 | C18: CUST-1354 | D18: P-2029 | E18: 2 | F18: =IF(E18<0,0,E18) -> 2 | G18: Online | H18: 0 | I18: =_xlfn.XLOOKUP(D18, 'retail_products'!$A:$A, 'retail_products'!$E:$E, "") -> 975.87 | J18: =_xlfn.XLOOKUP(D18, 'retail_products'!$A:$A, 'retail_products'!$D:$D, "") -> 397.97 | K18: =E18*I18 -> 1951.74 | L18: =K18*H18 -> 0 | M18: =K18-L18 -> 1951.74 | N18: =M18-(E18*J18) -> 1155.8 | O18: =TEXT(B18,"mmm") -> Dec
A19: ORD-50018 | B19: 45091 | C19: CUST-1390 | D19: P-2008 | E19: 4 | F19: =IF(E19<0,0,E19) -> 4 | G19: Mobile App | H19: 0.11 | I19: =_xlfn.XLOOKUP(D19, 'retail_products'!$A:$A, 'retail_products'!$E:$E, "") -> 821.38 | J19: =_xlfn.XLOOKUP(D19, 'retail_products'!$A:$A, 'retail_products'!$D:$D, "") -> 401.95 | K19: =E19*I19 -> 3285.52 | L19: =K19*H19 -> 361.4072 | M19: =K19-L19 -> 2924.1128 | N19: =M19-(E19*J19) -> 1316.3128 | O19: =TEXT(B19,"mmm") -> Jun
A20: ORD-50019 | B20: 45338 | C20: CUST-1520 | D20: P-2029 | E20: 4 | F20: =IF(E20<0,0,E20) -> 4 | G20: Mobile App | H20: 0 | I20: =_xlfn.XLOOKUP(D20, 'retail_products'!$A:$A, 'retail_products'!$E:$E, "") -> 975.87 | J20: =_xlfn.XLOOKUP(D20, 'retail_products'!$A:$A, 'retail_products'!$D:$D, "") -> 397.97 | K20: =E20*I20 -> 3903.48 | L20: =K20*H20 -> 0 | M20: =K20-L20 -> 3903.48 | N20: =M20-(E20*J20) -> 2311.6 | O20: =TEXT(B20,"mmm") -> Feb
A21: ORD-50020 | B21: 44976 | C21: CUST-1171 | D21: P-2050 | E21: 5 | F21: =IF(E21<0,0,E21) -> 5 | G21: Mobile App | H21: 0.26 | I21: =_xlfn.XLOOKUP(D21, 'retail_products'!$A:$A, 'retail_products'!$E:$E, "") -> 318.47 | J21: =_xlfn.XLOOKUP(D21, 'retail_products'!$A:$A, 'retail_products'!$D:$D, "") -> 231.89 | K21: =E21*I21 -> 1592.35 | L21: =K21*H21 -> 414.011 | M21: =K21-L21 -> 1178.339 | N21: =M21-(E21*J21) -> 18.889 | O21: =TEXT(B21,"mmm") -> Feb
A22: ORD-50021 | B22: 45144 | C22: CUST-1855 | D22: P-2007 | E22: 2 | F22: =IF(E22<0,0,E22) -> 2 | G22: In-Store | H22: 0 | I22: =_xlfn.XLOOKUP(D22, 'retail_products'!$A:$A, 'retail_products'!$E:$E, "") -> 243.64 | J22: =_xlfn.XLOOKUP(D22, 'retail_products'!$A:$A, 'retail_products'!$D:$D, "") -> 143.2 | K22: =E22*I22 -> 487.28 | L22: =K22*H22 -> 0 | M22: =K22-L22 -> 487.28 | N22: =M22-(E22*J22) -> 200.88 | O22: =TEXT(B22,"mmm") -> Aug
... A28: ORD-50027 | B28: 45007 | C28: CUST-1546 | D28: P-2015 | E28: 2 | F28: =IF(E28<0,0,E28) -> 2 | G28: In-Store | H28: 0.04 | I28: =_xlfn.XLOOKUP(D28, 'retail_products'!$A:$A, 'retail_products'!$E:$E, "") -> 37.4 | J28: =_xlfn.XLOOKUP(D28, 'retail_products'!$A:$A, 'retail_products'!$D:$D, "") -> 16.06 | K28: =E28*I28 -> 74.8 | L28: =K28*H28 -> 2.992 | M28: =K28-L28 -> 71.808 | N28: =M28-(E28*J28) -> 39.688 | O28: =TEXT(B28,"mmm") -> Mar
A29: ORD-50028 | B29: 12/13/23 | C29: CUST-1908 | D29: P-2047 | E29: 3 | F29: =IF(E29<0,0,E29) -> 3 | G29: Online | H29: 0 | I29: =_xlfn.XLOOKUP(D29, 'retail_products'!$A:$A, 'retail_products'!$E:$E, "") -> 124.81 | J29: =_xlfn.XLOOKUP(D29, 'retail_products'!$A:$A, 'retail_products'!$D:$D, "") -> 60.74 | K29: =E29*I29 -> 374.43 | L29: =K29*H29 -> 0 | M29: =K29-L29 -> 374.43 | N29: =M29-(E29*J29) -> 192.21 | O29: =TEXT(B29,"mmm") -> 12/13/23
A30: ORD-50029 | B30: 44929 | C30: CUST-1586 | D30: P-2039 | E30: 4 | F30: =IF(E30<0,0,E30) -> 4 | G30: Mobile App | H30: 0.22 | I30: =_xlfn.XLOOKUP(D30, 'retail_products'!$A:$A, 'retail_products'!$E:$E, "") -> 796.89 | J30: =_xlfn.XLOOKUP(D30, 'retail_products'!$A:$A, 'retail_products'!$D:$D, "") -> 465.81 | K30: =E30*I30 -> 3187.56 | L30: =K30*H30 -> 701.2632 | M30: =K30-L30 -> 2486.2968 | N30: =M30-(E30*J30) -> 623.0568 | O30: =TEXT(B30,"mmm") -> Jan
A31: ORD-50030 | B31: 45035 | C31: CUST-1422 | D31: P-2042 | E31: 5 | F31: =IF(E31<0,0,E31) -> 5 | G31: In-Store | H31: 0 | I31: =_xlfn.XLOOKUP(D31, 'retail_products'!$A:$A, 'retail_products'!$E:$E, "") -> 693.46 | J31: =_xlfn.XLOOKUP(D31, 'retail_products'!$A:$A, 'retail_products'!$D:$D, "") -> 388.35 | K31: =E31*I31 -> 3467.3 | L31: =K31*H31 -> 0 | M31: =K31-L31 -> 3467.3 | N31: =M31-(E31*J31) -> 1525.55 | O31: =TEXT(B31,"mmm") -> Apr
A32: ORD-50031 | B32: 45019 | C32: CUST-1687 | D32: P-2037 | E32: 1 | F32: =IF(E32<0,0,E32) -> 1 | G32: In-Store | H32: 0 | I32: =_xlfn.XLOOKUP(D32, 'retail_products'!$A:$A, 'retail_products'!$E:$E, "") -> 827.09 | J32: =_xlfn.XLOOKUP(D32, 'retail_products'!$A:$A, 'retail_products'!$D:$D, "") -> 449.47 | K32: =E32*I32 -> 827.09 | L32: =K32*H32 -> 0 | M32: =K32-L32 -> 827.09 | N32: =M32-(E32*J32) -> 377.62 | O32: =TEXT(B32,"mmm") -> Apr
A33: ORD-50032 | B33: 44964 | C33: CUST-1297 | D33: P-2043 | E33: 1 | F33: =IF(E33<0,0,E33) -> 1 | G33: In-Store | H33: 0 | I33: =_xlfn.XLOOKUP(D33, 'retail_products'!$A:$A, 'retail_products'!$E:$E, "") -> 657.99 | J33: =_xlfn.XLOOKUP(D33, 'retail_products'!$A:$A, 'retail_products'!$D:$D, "") -> 478.53 | K33: =E33*I33 -> 657.99 | L33: =K33*H33 -> 0 | M33: =K33-L33 -> 657.99 | N33: =M33-(E33*J33) -> 179.46 | O33: =TEXT(B33,"mmm") -> Feb
A34: ORD-50033 | B34: 45270 | C34: CUST-1671 | D34: P-2016 | E34: 1 | F34: =IF(E34<0,0,E34) -> 1 | G34: In-Store | H34: 0 | I34: =_xlfn.XLOOKUP(D34, 'retail_products'!$A:$A, 'retail_products'!$E:$E, "") -> 543.76 | J34: =_xlfn.XLOOKUP(D34, 'retail_products'!$A:$A, 'retail_products'!$D:$D, "") -> 364.65 | K34: =E34*I34 -> 543.76 | L34: =K34*H34 -> 0 | M34: =K34-L34 -> 543.76 | N34: =M34-(E34*J34) -> 179.11 | O34: =TEXT(B34,"mmm") -> Dec
A35: ORD-50034 | B35: 45242 | C35: CUST-1675 | D35: P-2020 | E35: 5 | F35: =IF(E35<0,0,E35) -> 5 | G35: In-Store | H35: 0 | I35: =_xlfn.XLOOKUP(D35, 'retail_products'!$A:$A, 'retail_products'!$E:$E, "") -> 892.78 | J35: =_xlfn.XLOOKUP(D35, 'retail_products'!$A:$A, 'retail_products'!$D:$D, "") -> 447.11 | K35: =E35*I35 -> 4463.9 | L35: =K35*H35 -> 0 | M35: =K35-L35 -> 4463.9 | N35: =M35-(E35*J35) -> 2228.35 | O35: =TEXT(B35,"mmm") -> Nov
A36: ORD-50035 | B36: 45087 | C36: CUST-1252 | D36: P-2015 | E36: 4 | F36: =IF(E36<0,0,E36) -> 4 | G36: In-Store | H36: 0.14 | I36: =_xlfn.XLOOKUP(D36, 'retail_products'!$A:$A, 'retail_products'!$E:$E, "") -> 37.4 | J36: =_xlfn.XLOOKUP(D36, 'retail_products'!$A:$A, 'retail_products'!$D:$D, "") -> 16.06 | K36: =E36*I36 -> 149.6 | L36: =K36*H36 -> 20.944 | M36: =K36-L36 -> 128.656 | N36: =M36-(E36*J36) -> 64.416 | O36: =TEXT(B36,"mmm") -> Jun
A37: ORD-50036 | B37: 45110 | C37: CUST-1793 | D37: P-2020 | E37: 4 | F37: =IF(E37<0,0,E37) -> 4 | G37: In-Store | H37: 0.04 | I37: =_xlfn.XLOOKUP(D37, 'retail_products'!$A:$A, 'retail_products'!$E:$E, "") -> 892.78 | J37: =_xlfn.XLOOKUP(D37, 'retail_products'!$A:$A, 'retail_products'!$D:$D, "") -> 447.11 | K37: =E37*I37 -> 3571.12 | L37: =K37*H37 -> 142.8448 | M37: =K37-L37 -> 3428.2752 | N37: =M37-(E37*J37) -> 1639.8352 | O37: =TEXT(B37,"mmm") -> Jul
A38: ORD-50037 | B38: 45202 | C38: CUST-1201 | D38: P-2017 | E38: 1 | F38: =IF(E38<0,0,E38) -> 1 | G38: Mobile App | H38: 0 | I38: =_xlfn.XLOOKUP(D38, 'retail_products'!$A:$A, 'retail_products'!$E:$E, "") -> 553.76 | J38: =_xlfn.XLOOKUP(D38, 'retail_products'!$A:$A, 'retail_products'!$D:$D, "") -> 264.36 | K38: =E38*I38 -> 553.76 | L38: =K38*H38 -> 0 | M38: =K38-L38 -> 553.76 | N38: =M38-(E38*J38) -> 289.4 | O38: =TEXT(B38,"mmm") -> Oct
A39: ORD-50038 | B39: 45224 | C39: CUST-1592 | D39: P-2026 | E39: 5 | F39: =IF(E39<0,0,E39) -> 5 | G39: Mobile App | H39: 0 | I39: =_xlfn.XLOOKUP(D39, 'retail_products'!$A:$A, 'retail_products'!$E:$E, "") -> 765.43 | J39: =_xlfn.XLOOKUP(D39, 'retail_products'!$A:$A, 'retail_products'!$D:$D, "") -> 429.73 | K39: =E39*I39 -> 3827.15 | L39: =K39*H39 -> 0 | M39: =K39-L39 -> 3827.15 | N39: =M39-(E39*J39) -> 1678.5 | O39: =TEXT(B39,"mmm") -> Oct
A40: ORD-50039 | B40: 45323 | C40: CUST-1152 | D40: P-2024 | E40: 4 | F40: =IF(E40<0,0,E40) -> 4 | G40: In-Store | H40: 0 | I40: =_xlfn.XLOOKUP(D40, 'retail_products'!$A:$A, 'retail_products'!$E:$E, "") -> 560.78 | J40: =_xlfn.XLOOKUP(D40, 'retail_products'!$A:$A, 'retail_products'!$D:$D, "") -> 325.23 | K40: =E40*I40 -> 2243.12 | L40: =K40*H40 -> 0 | M40: =K40-L40 -> 2243.12 | N40: =M40-(E40*J40) -> 942.2 | O40: =TEXT(B40,"mmm") -> Feb
A41: ORD-50040 | B41: 09/14/23 | C41: CUST-1522 | D41: P-2006 | E41: 4 | F41: =IF(E41<0,0,E41) -> 4 | G41: Mobile App | H41: 0 | I41: =_xlfn.XLOOKUP(D41, 'retail_products'!$A:$A, 'retail_products'!$E:$E, "") -> 171.43 | J41: =_xlfn.XLOOKUP(D41, 'retail_products'!$A:$A, 'retail_products'!$D:$D, "") -> 99.61 | K41: =E41*I41 -> 685.72 | L41: =K41*H41 -> 0 | M41: =K41-L41 -> 685.72 | N41: =M41-(E41*J41) -> 287.28 | O41: =TEXT(B41,"mmm") -> 09/14/23
A42: ORD-50041 | B42: 45314 | C42: CUST-1526 | D42: P-2009 | E42: 4 | F42: =IF(E42<0,0,E42) -> 4 | G42: Online | H42: 0.15 | I42: =_xlfn.XLOOKUP(D42, 'retail_products'!$A:$A, 'retail_products'!$E:$E, "") -> 137.67 | J42: =_xlfn.XLOOKUP(D42, 'retail_products'!$A:$A, 'retail_products'!$D:$D, "") -> 65.4 | K42: =E42*I42 -> 550.68 | L42: =K42*H42 -> 82.602 | M42: =K42-L42 -> 468.078 | N42: =M42-(E42*J42) -> 206.478 | O42: =TEXT(B42,"mmm") -> Jan
A43: ORD-50042 | B43: 45110 | C43: CUST-1041 | D43: P-2015 | E43: 4 | F43: =IF(E43<0,0,E43) -> 4 | G43: Mobile App | H43: 0 | I43: =_xlfn.XLOOKUP(D43, 'retail_products'!$A:$A, 'retail_products'!$E:$E, "") -> 37.4 | J43: =_xlfn.XLOOKUP(D43, 'retail_products'!$A:$A, 'retail_products'!$D:$D, "") -> 16.06 | K43: =E43*I43 -> 149.6 | L43: =K43*H43 -> 0 | M43: =K43-L43 -> 149.6 | N43: =M43-(E43*J43) -> 85.36 | O43: =TEXT(B43,"mmm") -> Jul
A44: ORD-50043 | B44: 45332 | C44: CUST-1369 | D44: P-2025 | E44: 4 | F44: =IF(E44<0,0,E44) -> 4 | G44: Mobile App | H44: 0 | I44: =_xlfn.XLOOKUP(D44, 'retail_products'!$A:$A, 'retail_products'!$E:$E, "") -> 526.7 | J44: =_xlfn.XLOOKUP(D44, 'retail_products'!$A:$A, 'retail_products'!$D:$D, "") -> 234.96 | K44: =E44*I44 -> 2106.8 | L44: =K44*H44 -> 0 | M44: =K44-L44 -> 2106.8 | N44: =M44-(E44*J44) -> 1166.96 | O44: =TEXT(B44,"mmm") -> Feb
A45: ORD-50044 | B45: 45287 | C45: CUST-1991 | D45: P-2034 | E45: 3 | F45: =IF(E45<0,0,E45) -> 3 | G45: Online | H45: 0 | I45: =_xlfn.XLOOKUP(D45, 'retail_products'!$A:$A, 'retail_products'!$E:$E, "") -> 144.07 | J45: =_xlfn.XLOOKUP(D45, 'retail_products'!$A:$A, 'retail_products'!$D:$D, "") -> 65.87 | K45: =E45*I45 -> 432.21 | L45: =K45*H45 -> 0 | M45: =K45-L45 -> 432.21 | N45: =M45-(E45*J45) -> 234.6 | O45: =TEXT(B45,"mmm") -> Dec
A46: ORD-50045 | B46: 45120 | C46: CUST-1374 | D46: P-2038 | E46: 1 | F46: =IF(E46<0,0,E46) -> 1 | G46: Mobile App | H46: 0 | I46: =_xlfn.XLOOKUP(D46, 'retail_products'!$A:$A, 'retail_products'!$E:$E, "") -> 124.45 | J46: =_xlfn.XLOOKUP(D46, 'retail_products'!$A:$A, 'retail_products'!$D:$D, "") -> 62.41 | K46: =E46*I46 -> 124.45 | L46: =K46*H46 -> 0 | M46: =K46-L46 -> 124.45 | N46: =M46-(E46*J46) -> 62.04 | O46: =TEXT(B46,"mmm") -> Jul
A47: ORD-50046 | B47: 45345 | C47: CUST-1888 | D47: P-2023 | E47: -1 | F47: =IF(E47<0,0,E47) -> 0 | G47: Online | H47: 0 | I47: =_xlfn.XLOOKUP(D47, 'retail_products'!$A:$A, 'retail_products'!$E:$E, "") -> 614.21 | J47: =_xlfn.XLOOKUP(D47, 'retail_products'!$A:$A, 'retail_products'!$D:$D, "") -> 485.37 | K47: =E47*I47 -> -614.21 | L47: =K47*H47 -> 0 | M47: =K47-L47 -> -614.21 | N47: =M47-(E47*J47) -> -128.84 | O47: =TEXT(B47,"mmm") -> Feb
A48: ORD-50047 | B48: 45044 | C48: CUST-1078 | D48: P-2033 | E48: 3 | F48: =IF(E48<0,0,E48) -> 3 | G48: Mobile App | H48: 0.2 | I48: =_xlfn.XLOOKUP(D48, 'retail_products'!$A:$A, 'retail_products'!$E:$E, "") -> 647.98 | J48: =_xlfn.XLOOKUP(D48, 'retail_products'!$A:$A, 'retail_products'!$D:$D, "") -> 303.98 | K48: =E48*I48 -> 1943.94 | L48: =K48*H48 -> 388.788 | M48: =K48-L48 -> 1555.152 | N48: =M48-(E48*J48) -> 643.212 | O48: =TEXT(B48,"mmm") -> Apr
A49: ORD-50048 | B49: 45139 | C49: CUST-1830 | D49: P-2022 | E49: 1 | F49: =IF(E49<0,0,E49) -> 1 | G49: Online | H49: 0 | I49: =_xlfn.XLOOKUP(D49, 'retail_products'!$A:$A, 'retail_products'!$E:$E, "") -> 85.85 | J49: =_xlfn.XLOOKUP(D49, 'retail_products'!$A:$A, 'retail_products'!$D:$D, "") -> 46.68 | K49: =E49*I49 -> 85.85 | L49: =K49*H49 -> 0 | M49: =K49-L49 -> 85.85 | N49: =M49-(E49*J49) -> 39.17 | O49: =TEXT(B49,"mmm") -> Aug
A50: ORD-50049 | B50: 45137 | C50: CUST-1022 | D50: P-2016 | E50: 1 | F50: =IF(E50<0,0,E50) -> 1 | G50: Mobile App | H50: 0 | I50: =_xlfn.XLOOKUP(D50, 'retail_products'!$A:$A, 'retail_products'!$E:$E, "") -> 543.76 | J50: =_xlfn.XLOOKUP(D50, 'retail_products'!$A:$A, 'retail_products'!$D:$D, "") -> 364.65 | K50: =E50*I50 -> 543.76 | L50: =K50*H50 -> 0 | M50: =K50-L50 -> 543.76 | N50: =M50-(E50*J50) -> 179.11 | O50: =TEXT(B50,"mmm") -> Jul
A51: ORD-50050 | B51: 45220 | C51: CUST-1150 | D51: P-2004 | E51: 2 | F51: =IF(E51<0,0,E51) -> 2 | G51: Mobile App | H51: 0.19 | I51: =_xlfn.XLOOKUP(D51, 'retail_products'!$A:$A, 'retail_products'!$E:$E, "") -> 404.15 | J51: =_xlfn.XLOOKUP(D51, 'retail_products'!$A:$A, 'retail_products'!$D:$D, "") -> 171.04 | K51: =E51*I51 -> 808.3 | L51: =K51*H51 -> 153.577 | M51: =K51-L51 -> 654.723 | N51: =M51-(E51*J51) -> 312.643 | O51: =TEXT(B51,"mmm") -> Oct
A52: ORD-50051 | B52: 45376 | C52: CUST-1736 | D52: P-2047 | E52: 3 | F52: =IF(E52<0,0,E52) -> 3 | G52: In-Store | H52: 0.05 | I52: =_xlfn.XLOOKUP(D52, 'retail_products'!$A:$A, 'retail_products'!$E:$E, "") -> 124.81 | J52: =_xlfn.XLOOKUP(D52, 'retail_products'!$A:$A, 'retail_products'!$D:$D, "") -> 60.74 | K52: =E52*I52 -> 374.43 | L52: =K52*H52 -> 18.7215 | M52: =K52-L52 -> 355.7085 | N52: =M52-(E52*J52) -> 173.4885 | O52: =TEXT(B52,"mmm") -> Mar
A53: ORD-50052 | B53: 45352 | C53: CUST-1420 | D53: P-2039 | E53: 2 | F53: =IF(E53<0,0,E53) -> 2 | G53: Mobile App | H53: 0 | I53: =_xlfn.XLOOKUP(D53, 'retail_products'!$A:$A, 'retail_products'!$E:$E, "") -> 796.89 | J53: =_xlfn.XLOOKUP(D53, 'retail_products'!$A:$A, 'retail_products'!$D:$D, "") -> 465.81 | K53: =E53*I53 -> 1593.78 | L53: =K53*H53 -> 0 | M53: =K53-L53 -> 1593.78 | N53: =M53-(E53*J53) -> 662.16 | O53: =TEXT(B53,"mmm") -> Mar
... A91: ORD-50090 | B91: 44957 | C91: CUST-1220 | D91: P-2017 | E91: 4 | F91: =IF(E91<0,0,E91) -> 4 | G91: In-Store | H91: 0 | I91: =_xlfn.XLOOKUP(D91, 'retail_products'!$A:$A, 'retail_products'!$E:$E, "") -> 553.76 | J91: =_xlfn.XLOOKUP(D91, 'retail_products'!$A:$A, 'retail_products'!$D:$D, "") -> 264.36 | K91: =E91*I91 -> 2215.04 | L91: =K91*H91 -> 0 | M91: =K91-L91 -> 2215.04 | N91: =M91-(E91*J91) -> 1157.6 | O91: =TEXT(B91,"mmm") -> Jan
B92: 45213 | C92: CUST-1570 | D92: P-2017 | E92: 3 | F92: =IF(E92<0,0,E92) -> 3 | G92: Mobile App | H92: 0 | I92: =_xlfn.XLOOKUP(D92, 'retail_products'!$A:$A, 'retail_products'!$E:$E, "") -> 553.76 | J92: =_xlfn.XLOOKUP(D92, 'retail_products'!$A:$A, 'retail_products'!$D:$D, "") -> 264.36 | K92: =E92*I92 -> 1661.28 | L92: =K92*H92 -> 0 | M92: =K92-L92 -> 1661.28 | N92: =M92-(E92*J92) -> 868.2 | O92: =TEXT(B92,"mmm") -> Oct
A93: ORD-50092 | B93: 45221 | C93: CUST-1665 | D93: P-2042 | E93: 5 | F93: =IF(E93<0,0,E93) -> 5 | G93: Mobile App | H93: 0 | I93: =_xlfn.XLOOKUP(D93, 'retail_products'!$A:$A, 'retail_products'!$E:$E, "") -> 693.46 | J93: =_xlfn.XLOOKUP(D93, 'retail_products'!$A:$A, 'retail_products'!$D:$D, "") -> 388.35 | K93: =E93*I93 -> 3467.3 | L93: =K93*H93 -> 0 | M93: =K93-L93 -> 3467.3 | N93: =M93-(E93*J93) -> 1525.55 | O93: =TEXT(B93,"mmm") -> Oct
A94: ORD-50093 | B94: 45323 | C94: CUST-1754 | D94: P-2029 | E94: 1 | F94: =IF(E94<0,0,E94) -> 1 | G94: Online | H94: 0.19 | I94: =_xlfn.XLOOKUP(D94, 'retail_products'!$A:$A, 'retail_products'!$E:$E, "") -> 975.87 | J94: =_xlfn.XLOOKUP(D94, 'retail_products'!$A:$A, 'retail_products'!$D:$D, "") -> 397.97 | K94: =E94*I94 -> 975.87 | L94: =K94*H94 -> 185.4153 | M94: =K94-L94 -> 790.4547 | N94: =M94-(E94*J94) -> 392.4847 | O94: =TEXT(B94,"mmm") -> Feb
A95: ORD-50094 | B95: 45099 | C95: CUST-1431 | D95: P-2041 | E95: 5 | F95: =IF(E95<0,0,E95) -> 5 | G95: Online | H95: 0 | I95: =_xlfn.XLOOKUP(D95, 'retail_products'!$A:$A, 'retail_products'!$E:$E, "") -> 1062.07 | J95: =_xlfn.XLOOKUP(D95, 'retail_products'!$A:$A, 'retail_products'!$D:$D, "") -> 464.05 | K95: =E95*I95 -> 5310.35 | L95: =K95*H95 -> 0 | M95: =K95-L95 -> 5310.35 | N95: =M95-(E95*J95) -> 2990.1 | O95: =TEXT(B95,"mmm") -> Jun
A96: ORD-50095 | B96: 45087 | C96: CUST-1324 | D96: P-2042 | E96: 3 | F96: =IF(E96<0,0,E96) -> 3 | G96: In-Store | H96: 0.28 | I96: =_xlfn.XLOOKUP(D96, 'retail_products'!$A:$A, 'retail_products'!$E:$E, "") -> 693.46 | J96: =_xlfn.XLOOKUP(D96, 'retail_products'!$A:$A, 'retail_products'!$D:$D, "") -> 388.35 | K96: =E96*I96 -> 2080.38 | L96: =K96*H96 -> 582.5064 | M96: =K96-L96 -> 1497.8736 | N96: =M96-(E96*J96) -> 332.8236 | O96: =TEXT(B96,"mmm") -> Jun
A97: ORD-50096 | B97: 45309 | C97: CUST-1601 | D97: P-2034 | E97: 4 | F97: =IF(E97<0,0,E97) -> 4 | G97: Mobile App | H97: 0 | I97: =_xlfn.XLOOKUP(D97, 'retail_products'!$A:$A, 'retail_products'!$E:$E, "") -> 144.07 | J97: =_xlfn.XLOOKUP(D97, 'retail_products'!$A:$A, 'retail_products'!$D:$D, "") -> 65.87 | K97: =E97*I97 -> 576.28 | L97: =K97*H97 -> 0 | M97: =K97-L97 -> 576.28 | N97: =M97-(E97*J97) -> 312.8 | O97: =TEXT(B97,"mmm") -> Jan
A98: ORD-50097 | B98: 45055 | C98: CUST-1963 | D98: P-2048 | E98: 1 | F98: =IF(E98<0,0,E98) -> 1 | G98: In-Store | H98: 0 | I98: =_xlfn.XLOOKUP(D98, 'retail_products'!$A:$A, 'retail_products'!$E:$E, "") -> 436.93 | J98: =_xlfn.XLOOKUP(D98, 'retail_products'!$A:$A, 'retail_products'!$D:$D, "") -> 257.01 | K98: =E98*I98 -> 436.93 | L98: =K98*H98 -> 0 | M98: =K98-L98 -> 436.93 | N98: =M98-(E98*J98) -> 179.92 | O98: =TEXT(B98,"mmm") -> May
A99: ORD-50098 | B99: 44940 | C99: CUST-1789 | D99: P-2026 | E99: 5 | F99: =IF(E99<0,0,E99) -> 5 | G99: Online | H99: 0 | I99: =_xlfn.XLOOKUP(D99, 'retail_products'!$A:$A, 'retail_products'!$E:$E, "") -> 765.43 | J99: =_xlfn.XLOOKUP(D99, 'retail_products'!$A:$A, 'retail_products'!$D:$D, "") -> 429.73 | K99: =E99*I99 -> 3827.15 | L99: =K99*H99 -> 0 | M99: =K99-L99 -> 3827.15 | N99: =M99-(E99*J99) -> 1678.5 | O99: =TEXT(B99,"mmm") -> Jan
A100: ORD-50099 | B100: 45126 | C100: CUST-1316 | D100: P-2015 | E100: 2 | F100: =IF(E100<0,0,E100) -> 2 | G100: Mobile App | H100: 0.01 | I100: =_xlfn.XLOOKUP(D100, 'retail_products'!$A:$A, 'retail_products'!$E:$E, "") -> 37.4 | J100: =_xlfn.XLOOKUP(D100, 'retail_products'!$A:$A, 'retail_products'!$D:$D, "") -> 16.06 | K100: =E100*I100 -> 74.8 | L100: =K100*H100 -> 0.748 | M100: =K100-L100 -> 74.052 | N100: =M100-(E100*J100) -> 41.932 | O100: =TEXT(B100,"mmm") -> Jul
A101: ORD-50100 | B101: 45266 | C101: CUST-1365 | D101: P-2021 | E101: 4 | F101: =IF(E101<0,0,E101) -> 4 | G101: Mobile App | H101: 0 | I101: =_xlfn.XLOOKUP(D101, 'retail_products'!$A:$A, 'retail_products'!$E:$E, "") -> 466.51 | J101: =_xlfn.XLOOKUP(D101, 'retail_products'!$A:$A, 'retail_products'!$D:$D, "") -> 257.73 | K101: =E101*I101 -> 1866.04 | L101: =K101*H101 -> 0 | M101: =K101-L101 -> 1866.04 | N101: =M101-(E101*J101) -> 835.12 | O101: =TEXT(B101,"mmm") -> Dec
A102: ORD-50101 | B102: 45284 | C102: CUST-1552 | D102: P-2012 | E102: 5 | F102: =IF(E102<0,0,E102) -> 5 | G102: Mobile App | H102: 0 | I102: =_xlfn.XLOOKUP(D102, 'retail_products'!$A:$A, 'retail_products'!$E:$E, "") -> 718.62 | J102: =_xlfn.XLOOKUP(D102, 'retail_products'!$A:$A, 'retail_products'!$D:$D, "") -> 309.57 | K102: =E102*I102 -> 3593.1 | L102: =K102*H102 -> 0 | M102: =K102-L102 -> 3593.1 | N102: =M102-(E102*J102) -> 2045.25 | O102: =TEXT(B102,"mmm") -> Dec
A103: ORD-50102 | B103: 45254 | C103: CUST-1654 | D103: P-2035 | E103: 3 | F103: =IF(E103<0,0,E103) -> 3 | G103: Online | H103: 0 | I103: =_xlfn.XLOOKUP(D103, 'retail_products'!$A:$A, 'retail_products'!$E:$E, "") -> 403.95 | J103: =_xlfn.XLOOKUP(D103, 'retail_products'!$A:$A, 'retail_products'!$D:$D, "") -> 177.26 | K103: =E103*I103 -> 1211.85 | L103: =K103*H103 -> 0 | M103: =K103-L103 -> 1211.85 | N103: =M103-(E103*J103) -> 680.07 | O103: =TEXT(B103,"mmm") -> Nov
A104: ORD-50103 | B104: 45114 | C104: CUST-1422 | D104: P-2017 | E104: 2 | F104: =IF(E104<0,0,E104) -> 2 | G104: Online | H104: 0 | I104: =_xlfn.XLOOKUP(D104, 'retail_products'!$A:$A, 'retail_products'!$E:$E, "") -> 553.76 | J104: =_xlfn.XLOOKUP(D104, 'retail_products'!$A:$A, 'retail_products'!$D:$D, "") -> 264.36 | K104: =E104*I104 -> 1107.52 | L104: =K104*H104 -> 0 | M104: =K104-L104 -> 1107.52 | N104: =M104-(E104*J104) -> 578.8 | O104: =TEXT(B104,"mmm") -> Jul
... A117: ORD-50116 | B117: 44953 | C117: CUST-1884 | D117: P-2043 | E117: 2 | F117: =IF(E117<0,0,E117) -> 2 | G117: Online | H117: 0 | I117: =_xlfn.XLOOKUP(D117, 'retail_products'!$A:$A, 'retail_products'!$E:$E, "") -> 657.99 | J117: =_xlfn.XLOOKUP(D117, 'retail_products'!$A:$A, 'retail_products'!$D:$D, "") -> 478.53 | K117: =E117*I117 -> 1315.98 | L117: =K117*H117 -> 0 | M117: =K117-L117 -> 1315.98 | N117: =M117-(E117*J117) -> 358.92 | O117: =TEXT(B117,"mmm") -> Jan
A118: ORD-50117 | B118: 05/22/23 | C118: CUST-1598 | D118: P-2008 | E118: 4 | F118: =IF(E118<0,0,E118) -> 4 | G118: Mobile App | H118: 0 | I118: =_xlfn.XLOOKUP(D118, 'retail_products'!$A:$A, 'retail_products'!$E:$E, "") -> 821.38 | J118: =_xlfn.XLOOKUP(D118, 'retail_products'!$A:$A, 'retail_products'!$D:$D, "") -> 401.95 | K118: =E118*I118 -> 3285.52 | L118: =K118*H118 -> 0 | M118: =K118-L118 -> 3285.52 | N118: =M118-(E118*J118) -> 1677.72 | O118: =TEXT(B118,"mmm") -> 05/22/23
A119: ORD-50118 | B119: 45232 | C119: CUST-1158 | D119: P-2024 | E119: 1 | F119: =IF(E119<0,0,E119) -> 1 | G119: In-Store | H119: 0.3 | I119: =_xlfn.XLOOKUP(D119, 'retail_products'!$A:$A, 'retail_products'!$E:$E, "") -> 560.78 | J119: =_xlfn.XLOOKUP(D119, 'retail_products'!$A:$A, 'retail_products'!$D:$D, "") -> 325.23 | K119: =E119*I119 -> 560.78 | L119: =K119*H119 -> 168.234 | M119: =K119-L119 -> 392.546 | N119: =M119-(E119*J119) -> 67.316 | O119: =TEXT(B119,"mmm") -> Nov
A120: ORD-50119 | B120: 45247 | C120: CUST-1061 | D120: P-2004 | E120: 3 | F120: =IF(E120<0,0,E120) -> 3 | G120: Online | H120: 0 | I120: =_xlfn.XLOOKUP(D120, 'retail_products'!$A:$A, 'retail_products'!$E:$E, "") -> 404.15 | J120: =_xlfn.XLOOKUP(D120, 'retail_products'!$A:$A, 'retail_products'!$D:$D, "") -> 171.04 | K120: =E120*I120 -> 1212.45 | L120: =K120*H120 -> 0 | M120: =K120-L120 -> 1212.45 | N120: =M120-(E120*J120) -> 699.33 | O120: =TEXT(B120,"mmm") -> Nov
A121: ORD-50120 | B121: 45089 | C121: CUST-1571 | D121: P-2042 | E121: 3 | F121: =IF(E121<0,0,E121) -> 3 | G121: Mobile App | H121: 0 | I121: =_xlfn.XLOOKUP(D121, 'retail_products'!$A:$A, 'retail_products'!$E:$E, "") -> 693.46 | J121: =_xlfn.XLOOKUP(D121, 'retail_products'!$A:$A, 'retail_products'!$D:$D, "") -> 388.35 | K121: =E121*I121 -> 2080.38 | L121: =K121*H121 -> 0 | M121: =K121-L121 -> 2080.38 | N121: =M121-(E121*J121) -> 915.33 | O121: =TEXT(B121,"mmm") -> Jun
A122: ORD-50121 | B122: 45297 | C122: CUST-1137 | D122: P-2017 | E122: 1 | F122: =IF(E122<0,0,E122) -> 1 | G122: Mobile App | H122: 0 | I122: =_xlfn.XLOOKUP(D122, 'retail_products'!$A:$A, 'retail_products'!$E:$E, "") -> 553.76 | J122: =_xlfn.XLOOKUP(D122, 'retail_products'!$A:$A, 'retail_products'!$D:$D, "") -> 264.36 | K122: =E122*I122 -> 553.76 | L122: =K122*H122 -> 0 | M122: =K122-L122 -> 553.76 | N122: =M122-(E122*J122) -> 289.4 | O122: =TEXT(B122,"mmm") -> Jan
A123: ORD-50122 | B123: 45217 | C123: CUST-1191 | D123: P-2035 | E123: 3 | F123: =IF(E123<0,0,E123) -> 3 | G123: Mobile App | H123: 0.17 | I123: =_xlfn.XLOOKUP(D123, 'retail_products'!$A:$A, 'retail_products'!$E:$E, "") -> 403.95 | J123: =_xlfn.XLOOKUP(D123, 'retail_products'!$A:$A, 'retail_products'!$D:$D, "") -> 177.26 | K123: =E123*I123 -> 1211.85 | L123: =K123*H123 -> 206.0145 | M123: =K123-L123 -> 1005.8355 | N123: =M123-(E123*J123) -> 474.0555 | O123: =TEXT(B123,"mmm") -> Oct
A124: ORD-50123 | B124: 44962 | C124: CUST-1543 | D124: P-2010 | E124: 4 | F124: =IF(E124<0,0,E124) -> 4 | G124: Online | H124: 0.15 | I124: =_xlfn.XLOOKUP(D124, 'retail_products'!$A:$A, 'retail_products'!$E:$E, "") -> 145.03 | J124: =_xlfn.XLOOKUP(D124, 'retail_products'!$A:$A, 'retail_products'!$D:$D, "") -> 60.82 | K124: =E124*I124 -> 580.12 | L124: =K124*H124 -> 87.018 | M124: =K124-L124 -> 493.102 | N124: =M124-(E124*J124) -> 249.822 | O124: =TEXT(B124,"mmm") -> Feb
A125: ORD-50124 | B125: 45302 | C125: CUST-1189 | D125: P-2002 | E125: 5 | F125: =IF(E125<0,0,E125) -> 5 | G125: Mobile App | H125: 0 | I125: =_xlfn.XLOOKUP(D125, 'retail_products'!$A:$A, 'retail_products'!$E:$E, "") -> 295.45 | J125: =_xlfn.XLOOKUP(D125, 'retail_products'!$A:$A, 'retail_products'!$D:$D, "") -> 218.74 | K125: =E125*I125 -> 1477.25 | L125: =K125*H125 -> 0 | M125: =K125-L125 -> 1477.25 | N125: =M125-(E125*J125) -> 383.55 | O125: =TEXT(B125,"mmm") -> Jan
A126: ORD-50125 | B126: 45202 | C126: CUST-1838 | D126: P-2025 | E126: 2 | F126: =IF(E126<0,0,E126) -> 2 | G126: Mobile App | H126: 0 | I126: =_xlfn.XLOOKUP(D126, 'retail_products'!$A:$A, 'retail_products'!$E:$E, "") -> 526.7 | J126: =_xlfn.XLOOKUP(D126, 'retail_products'!$A:$A, 'retail_products'!$D:$D, "") -> 234.96 | K126: =E126*I126 -> 1053.4 | L126: =K126*H126 -> 0 | M126: =K126-L126 -> 1053.4 | N126: =M126-(E126*J126) -> 583.48 | O126: =TEXT(B126,"mmm") -> Oct
A127: ORD-50126 | B127: 45136 | C127: CUST-1656 | D127: P-2021 | E127: 1 | F127: =IF(E127<0,0,E127) -> 1 | G127: Online | H127: 0 | I127: =_xlfn.XLOOKUP(D127, 'retail_products'!$A:$A, 'retail_products'!$E:$E, "") -> 466.51 | J127: =_xlfn.XLOOKUP(D127, 'retail_products'!$A:$A, 'retail_products'!$D:$D, "") -> 257.73 | K127: =E127*I127 -> 466.51 | L127: =K127*H127 -> 0 | M127: =K127-L127 -> 466.51 | N127: =M127-(E127*J127) -> 208.78 | O127: =TEXT(B127,"mmm") -> Jul
A128: ORD-50127 | B128: 44943 | C128: CUST-1206 | D128: P-2007 | E128: 4 | F128: =IF(E128<0,0,E128) -> 4 | G128: In-Store | H128: 0 | I128: =_xlfn.XLOOKUP(D128, 'retail_products'!$A:$A, 'retail_products'!$E:$E, "") -> 243.64 | J128: =_xlfn.XLOOKUP(D128, 'retail_products'!$A:$A, 'retail_products'!$D:$D, "") -> 143.2 | K128: =E128*I128 -> 974.56 | L128: =K128*H128 -> 0 | M128: =K128-L128 -> 974.56 | N128: =M128-(E128*J128) -> 401.76 | O128: =TEXT(B128,"mmm") -> Jan
A129: ORD-50128 | B129: 45196 | C129: CUST-1638 | D129: P-2045 | E129: 5 | F129: =IF(E129<0,0,E129) -> 5 | G129: Online | H129: 0 | I129: =_xlfn.XLOOKUP(D129, 'retail_products'!$A:$A, 'retail_products'!$E:$E, "") -> 769.55 | J129: =_xlfn.XLOOKUP(D129, 'retail_products'!$A:$A, 'retail_products'!$D:$D, "") -> 421.02 | K129: =E129*I129 -> 3847.75 | L129: =K129*H129 -> 0 | M129: =K129-L129 -> 3847.75 | N129: =M129-(E129*J129) -> 1742.65 | O129: =TEXT(B129,"mmm") -> Sep
A130: ORD-50129 | B130: 45033 | C130: CUST-1671 | D130: P-2032 | E130: 1 | F130: =IF(E130<0,0,E130) -> 1 | G130: Mobile App | H130: 0.12 | I130: =_xlfn.XLOOKUP(D130, 'retail_products'!$A:$A, 'retail_products'!$E:$E, "") -> 691.33 | J130: =_xlfn.XLOOKUP(D130, 'retail_products'!$A:$A, 'retail_products'!$D:$D, "") -> 423.72 | K130: =E130*I130 -> 691.33 | L130: =K130*H130 -> 82.9596 | M130: =K130-L130 -> 608.3704 | N130: =M130-(E130*J130) -> 184.6504 | O130: =TEXT(B130,"mmm") -> Apr
... A149: ORD-50148 | B149: 45063 | C149: CUST-1795 | D149: P-2028 | E149: 3 | F149: =IF(E149<0,0,E149) -> 3 | G149: In-Store | H149: 0 | I149: =_xlfn.XLOOKUP(D149, 'retail_products'!$A:$A, 'retail_products'!$E:$E, "") -> 52.75 | J149: =_xlfn.XLOOKUP(D149, 'retail_products'!$A:$A, 'retail_products'!$D:$D, "") -> 27.56 | K149: =E149*I149 -> 158.25 | L149: =K149*H149 -> 0 | M149: =K149-L149 -> 158.25 | N149: =M149-(E149*J149) -> 75.57 | O149: =TEXT(B149,"mmm") -> May
A150: ORD-50149 | B150: 06/28/23 | C150: CUST-1195 | D150: P-2021 | E150: 3 | F150: =IF(E150<0,0,E150) -> 3 | G150: In-Store | H150: 0 | I150: =_xlfn.XLOOKUP(D150, 'retail_products'!$A:$A, 'retail_products'!$E:$E, "") -> 466.51 | J150: =_xlfn.XLOOKUP(D150, 'retail_products'!$A:$A, 'retail_products'!$D:$D, "") -> 257.73 | K150: =E150*I150 -> 1399.53 | L150: =K150*H150 -> 0 | M150: =K150-L150 -> 1399.53 | N150: =M150-(E150*J150) -> 626.34 | O150: =TEXT(B150,"mmm") -> 06/28/23
A151: ORD-50150 | B151: 45338 | C151: CUST-1452 | D151: P-2040 | E151: 2 | F151: =IF(E151<0,0,E151) -> 2 | G151: Mobile App | H151: 0 | I151: =_xlfn.XLOOKUP(D151, 'retail_products'!$A:$A, 'retail_products'!$E:$E, "") -> 484.08 | J151: =_xlfn.XLOOKUP(D151, 'retail_products'!$A:$A, 'retail_products'!$D:$D, "") -> 361.23 | K151: =E151*I151 -> 968.16 | L151: =K151*H151 -> 0 | M151: =K151-L151 -> 968.16 | N151: =M151-(E151*J151) -> 245.7 | O151: =TEXT(B151,"mmm") -> Feb
A152: ORD-50151 | B152: 45314 | C152: CUST-1745 | D152: P-2006 | E152: 1 | F152: =IF(E152<0,0,E152) -> 1 | G152: Online | H152: 0.25 | I152: =_xlfn.XLOOKUP(D152, 'retail_products'!$A:$A, 'retail_products'!$E:$E, "") -> 171.43 | J152: =_xlfn.XLOOKUP(D152, 'retail_products'!$A:$A, 'retail_products'!$D:$D, "") -> 99.61 | K152: =E152*I152 -> 171.43 | L152: =K152*H152 -> 42.8575 | M152: =K152-L152 -> 128.5725 | N152: =M152-(E152*J152) -> 28.9625 | O152: =TEXT(B152,"mmm") -> Jan
A153: ORD-50152 | B153: 44934 | C153: CUST-1351 | D153: P-2045 | E153: 1 | F153: =IF(E153<0,0,E153) -> 1 | G153: Mobile App | H153: 0 | I153: =_xlfn.XLOOKUP(D153, 'retail_products'!$A:$A, 'retail_products'!$E:$E, "") -> 769.55 | J153: =_xlfn.XLOOKUP(D153, 'retail_products'!$A:$A, 'retail_products'!$D:$D, "") -> 421.02 | K153: =E153*I153 -> 769.55 | L153: =K153*H153 -> 0 | M153: =K153-L153 -> 769.55 | N153: =M153-(E153*J153) -> 348.53 | O153: =TEXT(B153,"mmm") -> Jan
A154: ORD-50153 | B154: 45031 | C154: CUST-1559 | D154: P-2034 | E154: 3 | F154: =IF(E154<0,0,E154) -> 3 | G154: Mobile App | H154: 0 | I154: =_xlfn.XLOOKUP(D154, 'retail_products'!$A:$A, 'retail_products'!$E:$E, "") -> 144.07 | J154: =_xlfn.XLOOKUP(D154, 'retail_products'!$A:$A, 'retail_products'!$D:$D, "") -> 65.87 | K154: =E154*I154 -> 432.21 | L154: =K154*H154 -> 0 | M154: =K154-L154 -> 432.21 | N154: =M154-(E154*J154) -> 234.6 | O154: =TEXT(B154,"mmm") -> Apr
A155: ORD-50154 | B155: 44936 | C155: CUST-1385 | D155: P-2038 | E155: 5 | F155: =IF(E155<0,0,E155) -> 5 | G155: Mobile App | H155: 0 | I155: =_xlfn.XLOOKUP(D155, 'retail_products'!$A:$A, 'retail_products'!$E:$E, "") -> 124.45 | J155: =_xlfn.XLOOKUP(D155, 'retail_products'!$A:$A, 'retail_products'!$D:$D, "") -> 62.41 | K155: =E155*I155 -> 622.25 | L155: =K155*H155 -> 0 | M155: =K155-L155 -> 622.25 | N155: =M155-(E155*J155) -> 310.2 | O155: =TEXT(B155,"mmm") -> Jan
A156: ORD-50155 | B156: 44954 | C156: CUST-1476 | D156: P-2042 | E156: 1 | F156: =IF(E156<0,0,E156) -> 1 | G156: Mobile App | H156: 0 | I156: =_xlfn.XLOOKUP(D156, 'retail_products'!$A:$A, 'retail_products'!$E:$E, "") -> 693.46 | J156: =_xlfn.XLOOKUP(D156, 'retail_products'!$A:$A, 'retail_products'!$D:$D, "") -> 388.35 | K156: =E156*I156 -> 693.46 | L156: =K156*H156 -> 0 | M156: =K156-L156 -> 693.46 | N156: =M156-(E156*J156) -> 305.11 | O156: =TEXT(B156,"mmm") -> Jan
A157: ORD-50156 | B157: 44982 | C157: CUST-1019 | D157: P-2019 | E157: 4 | F157: =IF(E157<0,0,E157) -> 4 | G157: Online | H157: 0.15 | I157: =_xlfn.XLOOKUP(D157, 'retail_products'!$A:$A, 'retail_products'!$E:$E, "") -> 681.78 | J157: =_xlfn.XLOOKUP(D157, 'retail_products'!$A:$A, 'retail_products'!$D:$D, "") -> 335.22 | K157: =E157*I157 -> 2727.12 | L157: =K157*H157 -> 409.068 | M157: =K157-L157 -> 2318.052 | N157: =M157-(E157*J157) -> 977.172 | O157: =TEXT(B157,"mmm") -> Feb
A158: ORD-50157 | B158: 45232 | C158: CUST-1544 | D158: P-2006 | E158: 2 | F158: =IF(E158<0,0,E158) -> 2 | G158: Mobile App | H158: 0 | I158: =_xlfn.XLOOKUP(D158, 'retail_products'!$A:$A, 'retail_products'!$E:$E, "") -> 171.43 | J158: =_xlfn.XLOOKUP(D158, 'retail_products'!$A:$A, 'retail_products'!$D:$D, "") -> 99.61 | K158: =E158*I158 -> 342.86 | L158: =K158*H158 -> 0 | M158: =K158-L158 -> 342.86 | N158: =M158-(E158*J158) -> 143.64 | O158: =TEXT(B158,"mmm") -> Nov
A159: ORD-50158 | B159: 45053 | C159: CUST-1944 | D159: P-2034 | E159: 3 | F159: =IF(E159<0,0,E159) -> 3 | G159: In-Store | H159: 0 | I159: =_xlfn.XLOOKUP(D159, 'retail_products'!$A:$A, 'retail_products'!$E:$E, "") -> 144.07 | J159: =_xlfn.XLOOKUP(D159, 'retail_products'!$A:$A, 'retail_products'!$D:$D, "") -> 65.87 | K159: =E159*I159 -> 432.21 | L159: =K159*H159 -> 0 | M159: =K159-L159 -> 432.21 | N159: =M159-(E159*J159) -> 234.6 | O159: =TEXT(B159,"mmm") -> May
A160: ORD-50159 | B160: 45108 | C160: CUST-1640 | D160: P-2020 | E160: 2 | F160: =IF(E160<0,0,E160) -> 2 | G160: Online | H160: 0 | I160: =_xlfn.XLOOKUP(D160, 'retail_products'!$A:$A, 'retail_products'!$E:$E, "") -> 892.78 | J160: =_xlfn.XLOOKUP(D160, 'retail_products'!$A:$A, 'retail_products'!$D:$D, "") -> 447.11 | K160: =E160*I160 -> 1785.56 | L160: =K160*H160 -> 0 | M160: =K160-L160 -> 1785.56 | N160: =M160-(E160*J160) -> 891.34 | O160: =TEXT(B160,"mmm") -> Jul
A161: ORD-50160 | B161: 45376 | C161: CUST-1396 | D161: P-2002 | E161: 5 | F161: =IF(E161<0,0,E161) -> 5 | G161: In-Store | H161: 0 | I161: =_xlfn.XLOOKUP(D161, 'retail_products'!$A:$A, 'retail_products'!$E:$E, "") -> 295.45 | J161: =_xlfn.XLOOKUP(D161, 'retail_products'!$A:$A, 'retail_products'!$D:$D, "") -> 218.74 | K161: =E161*I161 -> 1477.25 | L161: =K161*H161 -> 0 | M161: =K161-L161 -> 1477.25 | N161: =M161-(E161*J161) -> 383.55 | O161: =TEXT(B161,"mmm") -> Mar
A162: ORD-50161 | B162: 44971 | C162: CUST-1747 | D162: P-2025 | E162: 5 | F162: =IF(E162<0,0,E162) -> 5 | G162: Online | H162: 0 | I162: =_xlfn.XLOOKUP(D162, 'retail_products'!$A:$A, 'retail_products'!$E:$E, "") -> 526.7 | J162: =_xlfn.XLOOKUP(D162, 'retail_products'!$A:$A, 'retail_products'!$D:$D, "") -> 234.96 | K162: =E162*I162 -> 2633.5 | L162: =K162*H162 -> 0 | M162: =K162-L162 -> 2633.5 | N162: =M162-(E162*J162) -> 1458.7 | O162: =TEXT(B162,"mmm") -> Feb
... A182: ORD-50181 | B182: 45001 | C182: CUST-1183 | D182: P-2050 | E182: 1 | F182: =IF(E182<0,0,E182) -> 1 | G182: In-Store | H182: 0 | I182: =_xlfn.XLOOKUP(D182, 'retail_products'!$A:$A, 'retail_products'!$E:$E, "") -> 318.47 | J182: =_xlfn.XLOOKUP(D182, 'retail_products'!$A:$A, 'retail_products'!$D:$D, "") -> 231.89 | K182: =E182*I182 -> 318.47 | L182: =K182*H182 -> 0 | M182: =K182-L182 -> 318.47 | N182: =M182-(E182*J182) -> 86.58 | O182: =TEXT(B182,"mmm") -> Mar
B183: 45019 | C183: CUST-1120 | D183: P-2009 | E183: -1 | F183: =IF(E183<0,0,E183) -> 0 | G183: In-Store | H183: 0.16 | I183: =_xlfn.XLOOKUP(D183, 'retail_products'!$A:$A, 'retail_products'!$E:$E, "") -> 137.67 | J183: =_xlfn.XLOOKUP(D183, 'retail_products'!$A:$A, 'retail_products'!$D:$D, "") -> 65.4 | K183: =E183*I183 -> -137.67 | L183: =K183*H183 -> -22.0272 | M183: =K183-L183 -> -115.6428 | N183: =M183-(E183*J183) -> -50.2428 | O183: =TEXT(B183,"mmm") -> Apr
A184: ORD-50183 | B184: 44929 | C184: CUST-1622 | D184: P-2032 | E184: 2 | F184: =IF(E184<0,0,E184) -> 2 | G184: In-Store | H184: 0 | I184: =_xlfn.XLOOKUP(D184, 'retail_products'!$A:$A, 'retail_products'!$E:$E, "") -> 691.33 | J184: =_xlfn.XLOOKUP(D184, 'retail_products'!$A:$A, 'retail_products'!$D:$D, "") -> 423.72 | K184: =E184*I184 -> 1382.66 | L184: =K184*H184 -> 0 | M184: =K184-L184 -> 1382.66 | N184: =M184-(E184*J184) -> 535.22 | O184: =TEXT(B184,"mmm") -> Jan
A185: ORD-50184 | B185: 45234 | C185: CUST-1006 | D185: P-2016 | E185: 5 | F185: =IF(E185<0,0,E185) -> 5 | G185: Online | H185: 0 | I185: =_xlfn.XLOOKUP(D185, 'retail_products'!$A:$A, 'retail_products'!$E:$E, "") -> 543.76 | J185: =_xlfn.XLOOKUP(D185, 'retail_products'!$A:$A, 'retail_products'!$D:$D, "") -> 364.65 | K185: =E185*I185 -> 2718.8 | L185: =K185*H185 -> 0 | M185: =K185-L185 -> 2718.8 | N185: =M185-(E185*J185) -> 895.55 | O185: =TEXT(B185,"mmm") -> Nov
A186: ORD-50185 | B186: 45002 | C186: CUST-1056 | D186: P-2042 | E186: 3 | F186: =IF(E186<0,0,E186) -> 3 | G186: Mobile App | H186: 0 | I186: =_xlfn.XLOOKUP(D186, 'retail_products'!$A:$A, 'retail_products'!$E:$E, "") -> 693.46 | J186: =_xlfn.XLOOKUP(D186, 'retail_products'!$A:$A, 'retail_products'!$D:$D, "") -> 388.35 | K186: =E186*I186 -> 2080.38 | L186: =K186*H186 -> 0 | M186: =K186-L186 -> 2080.38 | N186: =M186-(E186*J186) -> 915.33 | O186: =TEXT(B186,"mmm") -> Mar
A187: ORD-50186 | B187: 44971 | C187: CUST-1050 | D187: P-2007 | E187: 4 | F187: =IF(E187<0,0,E187) -> 4 | G187: Mobile App | H187: 0 | I187: =_xlfn.XLOOKUP(D187, 'retail_products'!$A:$A, 'retail_products'!$E:$E, "") -> 243.64 | J187: =_xlfn.XLOOKUP(D187, 'retail_products'!$A:$A, 'retail_products'!$D:$D, "") -> 143.2 | K187: =E187*I187 -> 974.56 | L187: =K187*H187 -> 0 | M187: =K187-L187 -> 974.56 | N187: =M187-(E187*J187) -> 401.76 | O187: =TEXT(B187,"mmm") -> Feb
A188: ORD-50187 | B188: 45231 | C188: CUST-1586 | D188: P-2036 | E188: 2 | F188: =IF(E188<0,0,E188) -> 2 | G188: Online | H188: 0 | I188: =_xlfn.XLOOKUP(D188, 'retail_products'!$A:$A, 'retail_products'!$E:$E, "") -> 469.35 | J188: =_xlfn.XLOOKUP(D188, 'retail_products'!$A:$A, 'retail_products'!$D:$D, "") -> 278.37 | K188: =E188*I188 -> 938.7 | L188: =K188*H188 -> 0 | M188: =K188-L188 -> 938.7 | N188: =M188-(E188*J188) -> 381.96 | O188: =TEXT(B188,"mmm") -> Nov
A189: ORD-50188 | B189: 45080 | C189: CUST-1330 | D189: P-2024 | E189: 4 | F189: =IF(E189<0,0,E189) -> 4 | G189: Online | H189: 0 | I189: =_xlfn.XLOOKUP(D189, 'retail_products'!$A:$A, 'retail_products'!$E:$E, "") -> 560.78 | J189: =_xlfn.XLOOKUP(D189, 'retail_products'!$A:$A, 'retail_products'!$D:$D, "") -> 325.23 | K189: =E189*I189 -> 2243.12 | L189: =K189*H189 -> 0 | M189: =K189-L189 -> 2243.12 | N189: =M189-(E189*J189) -> 942.2 | O189: =TEXT(B189,"mmm") -> Jun
A190: ORD-50189 | B190: 44995 | C190: CUST-1124 | D190: P-2045 | E190: 3 | F190: =IF(E190<0,0,E190) -> 3 | G190: Online | H190: 0 | I190: =_xlfn.XLOOKUP(D190, 'retail_products'!$A:$A, 'retail_products'!$E:$E, "") -> 769.55 | J190: =_xlfn.XLOOKUP(D190, 'retail_products'!$A:$A, 'retail_products'!$D:$D, "") -> 421.02 | K190: =E190*I190 -> 2308.65 | L190: =K190*H190 -> 0 | M190: =K190-L190 -> 2308.65 | N190: =M190-(E190*J190) -> 1045.59 | O190: =TEXT(B190,"mmm") -> Mar
A191: ORD-50190 | B191: 44982 | C191: CUST-1585 | D191: P-2047 | E191: 5 | F191: =IF(E191<0,0,E191) -> 5 | G191: Mobile App | H191: 0 | I191: =_xlfn.XLOOKUP(D191, 'retail_products'!$A:$A, 'retail_products'!$E:$E, "") -> 124.81 | J191: =_xlfn.XLOOKUP(D191, 'retail_products'!$A:$A, 'retail_products'!$D:$D, "") -> 60.74 | K191: =E191*I191 -> 624.05 | L191: =K191*H191 -> 0 | M191: =K191-L191 -> 624.05 | N191: =M191-(E191*J191) -> 320.35 | O191: =TEXT(B191,"mmm") -> Feb
...

Sheet Pivot Tables
A3: Total profit | E3: Total Revenue | I3: Total Orders | M3: Total Customers
A4: 1454389.3 | E4: 3601889.4 | I4: 2449 | M4: 931
N23: Row Labels | O23: Sum of profit
N24: Jan | O24: 206855.85
A25: Channels | B25: Total profit | N25: Feb | O25: 193123.92
A26: In-Store | B26: 472289.14 | N26: Mar | O26: 171580.77
A27: Mobile App | B27: 491236.37 | N27: Apr | O27: 89302.071
A28: Online | B28: 490863.8 | N28: May | O28: 98912.954
A29: Grand Total | B29: 1454389.3 | N29: Jun | O29: 102912.47
N30: Jul | O30: 98011.647
N31: Aug | O31: 85408.342
N32: Sep | O32: 95790.452
N33: Oct | O33: 93566.674
N34: Nov | O34: 104450.85
A35: Row Labels | B35: Sum of gross_revenue | H35: Row Labels | I35: Sum of gross_revenue | N35: Dec | O35: 114473.32
A36: In-Store | B36: 1178386.1 | H36: Jan | I36: 514309.74 | N36: Grand Total | O36: 1454389.3
A37: Mobile App | B37: 1223718.7 | H37: Feb | I37: 483593.76
A38: Online | B38: 1199784.7 | H38: Mar | I38: 442578.08
A39: Grand Total | B39: 3601889.4 | H39: Apr | I39: 220418.29
H40: May | I40: 239377.38
H41: Jun | I41: 251572.15
H42: Jul | I42: 241180.53
H43: Aug | I43: 213989.4
B44: Row Labels | C44: Sum of profit | H44: Sep | I44: 235579.08
B45: Jan | C45: 206855.85 | H45: Oct | I45: 228693.35
B46: Feb | C46: 193123.92 | H46: Nov | I46: 251098.73
B47: Mar | C47: 171580.77 | H47: Dec | I47: 279498.91
B48: Apr | C48: 89302.071 | H48: Grand Total | I48: 3601889.4
B49: May | C49: 98912.954
B50: Jun | C50: 102912.47
B51: Jul | C51: 98011.647
B52: Aug | C52: 85408.342
B53: Sep | C53: 95790.452
B54: Oct | C54: 93566.674
B55: Nov | C55: 104450.85
B56: Dec | C56: 114473.32
B57: Grand Total | C57: 1454389.3

Sheet Dashboard
A1: Retail Sales Performance Dashboard
A28: Dashboard created by Victor Weka Excel • Power Pivot • Pivot Tables

Sheet month
A1: month_no | B1: month
A2: 1 | B2: Jan
A3: 2 | B3: Feb
A4: 3 | B4: Mar
A5: 4 | B5: Apr
A6: 5 | B6: May
A7: 6 | B7: Jun
A8: 7 | B8: Jul
A9: 8 | B9: Aug
A10: 9 | B10: Sep
A11: 10 | B11: Oct
A12: 11 | B12: Nov
A13: 12 | B13: Dec
